comspy/__init__.py
comspy/developer/__init__.py
comspy/user/Client_Chinese.py
comspy/user/Client_English.py
comspy/user/Server_Chinese.py
comspy/user/Server_English.py
comspy/user/__init__.py
comspy-2022.3.dist-info/LICENSE
comspy-2022.3.dist-info/METADATA
comspy-2022.3.dist-info/WHEEL
comspy-2022.3.dist-info/top_level.txt
comspy-2022.3.dist-info/RECORD
