Metadata-Version: 2.1
Name: comspy
Version: 2022.3
Summary: A package that uses Python to make communication easier
Home-page: https://github.com/SunnyLi1106/ComsPy
Author: SunnyLi
Author-email: 5327136@qq.com
License: UNKNOWN
Platform: UNKNOWN
Classifier: Programming Language :: Python :: 3
Classifier: License :: OSI Approved :: MIT License
Classifier: Operating System :: OS Independent
Requires-Python: >=3
License-File: LICENSE
Requires-Dist: pyesytime
